faker_openai_api_provider/__init__.py
faker_openai_api_provider/__version__.py
faker_openai_api_provider/_assistants.py
faker_openai_api_provider/_chat.py
faker_openai_api_provider/_file.py
faker_openai_api_provider/_thread.py
faker_openai_api_provider/_utils.py
faker_openai_api_provider/_vector_store.py
faker_openai_api_provider/py.typed
faker_openai_api_provider-0.2.0.dist-info/LICENSE
faker_openai_api_provider-0.2.0.dist-info/METADATA
faker_openai_api_provider-0.2.0.dist-info/WHEEL
faker_openai_api_provider-0.2.0.dist-info/RECORD
