Metadata-Version: 2.1
Name: faker-openai-api-provider
Version: 0.2.0
Summary: Generate fake data that resembles fields in OpenAI API responses
Home-page: https://github.com/mharrisb1/faker-openai-api-provider
License: MIT
Author: Michael Harris
Author-email: mharris@definite.app
Requires-Python: >=3.9,<4.0
Classifier: License :: OSI Approved :: MIT License
Classifier: Programming Language :: Python :: 3
Classifier: Programming Language :: Python :: 3.9
Classifier: Programming Language :: Python :: 3.10
Classifier: Programming Language :: Python :: 3.11
Classifier: Programming Language :: Python :: 3.12
Requires-Dist: faker (>=24.2.0,<25.0.0)
Project-URL: Repository, https://github.com/mharrisb1/faker-openai-api-provider
